bits/__init__.py
bits/netbox/__init__.py
bits_netbox-1.3.4.dist-info/METADATA
bits_netbox-1.3.4.dist-info/WHEEL
bits_netbox-1.3.4.dist-info/top_level.txt
bits_netbox-1.3.4.dist-info/RECORD
